pywordseg/__init__.py
pywordseg/download.py
pywordseg/postprocessing.py
pywordseg/pywordseg.py
pywordseg-0.1.4.dist-info/LICENSE
pywordseg-0.1.4.dist-info/METADATA
pywordseg-0.1.4.dist-info/WHEEL
pywordseg-0.1.4.dist-info/top_level.txt
pywordseg-0.1.4.dist-info/RECORD
