Metadata-Version: 2.1
Name: pywordseg
Version: 0.1.4
Summary: Open source state-of-the-art Chinese word segmentation toolkit
Home-page: https://github.com/voidism/pywordseg
Author: Jexus Chuang
License: MIT
Platform: UNKNOWN
Classifier: Development Status :: 2 - Pre-Alpha
Classifier: Programming Language :: Python
Classifier: Programming Language :: Python :: 3.6
Requires-Dist: torch
Requires-Dist: h5py
Requires-Dist: numpy
Requires-Dist: overrides (==1.9)
